<?xml version="1.0" encoding="UTF-8" standalone="yes"?>
<ctModel>
    <contactlessDeviceStatus>Unknown</contactlessDeviceStatus>
    <cpList>
        <bootDttm>2017-12-21T20:16:11.525+08:00</bootDttm>
        <connected>false</connected>
        <connectedDttm>2017-12-26T13:41:45.877+08:00</connectedDttm>
        <cpNo>CP11</cpNo>
        <disconnectedDttm>2017-12-26T13:43:24.508+08:00</disconnectedDttm>
        <enabled>true</enabled>
        <lastReceivedDttm>2017-12-26T13:43:00.091+08:00</lastReceivedDttm>
        <lastSentDttm>2017-12-26T13:43:00.099+08:00</lastSentDttm>
        <status>Preparing</status>
        <statusDttm>2017-12-26T13:43:00.095+08:00</statusDttm>
        <tran>
            <actualEndDttm>2017-12-26T13:42:43.073+08:00</actualEndDttm>
            <amt>21.0</amt>
            <chargingUnitMinutes>30</chargingUnitMinutes>
            <cpNo>CP11</cpNo>
            <durationMin>90</durationMin>
            <durationOffPeak>0</durationOffPeak>
            <durationOnPeak>90</durationOnPeak>
            <endDttm>2017-12-26T15:11:59.385+08:00</endDttm>
            <energyCharge>0</energyCharge>
            <idTag>aecd5679-93d0-4b29-8f9f-3fe70783631b</idTag>
            <minChargingUnit>1</minChargingUnit>
            <payMethodCode>Contactless</payMethodCode>
            <receiptNo>20048</receiptNo>
            <startDttm>2017-12-26T13:41:59.385+08:00</startDttm>
            <timeCharge>21.0</timeCharge>
            <timeChargeOffPeak>0.0</timeChargeOffPeak>
            <timeChargeOnPeak>21.0</timeChargeOnPeak>
            <timeRateOffPeakPerUnit>7.000</timeRateOffPeakPerUnit>
            <timeRateOnPeakPerUnit>7.000</timeRateOnPeakPerUnit>
            <totChargingUnit>3</totChargingUnit>
            <tranDttm>2017-12-26T13:41:59.385+08:00</tranDttm>
            <tranId>20048</tranId>
            <tranStatusCode>Stopped</tranStatusCode>
        </tran>
    </cpList>
    <cpList>
        <connected>false</connected>
        <connectedDttm>2017-11-12T17:45:30.362+08:00</connectedDttm>
        <cpNo>CP12</cpNo>
        <enabled>true</enabled>
        <lastReceivedDttm>2017-11-12T17:46:16.137+08:00</lastReceivedDttm>
        <lastSentDttm>2017-11-12T17:46:16.137+08:00</lastSentDttm>
        <status>Available</status>
    </cpList>
    <cpList>
        <connected>false</connected>
        <connectedDttm>2017-11-12T17:30:31.052+08:00</connectedDttm>
        <cpNo>CP13</cpNo>
        <disconnectedDttm>2017-11-12T17:31:06.044+08:00</disconnectedDttm>
        <enabled>true</enabled>
        <lastReceivedDttm>2017-11-12T17:30:58.021+08:00</lastReceivedDttm>
        <lastSentDttm>2017-11-12T17:30:58.018+08:00</lastSentDttm>
        <status>Unavailable</status>
    </cpList>
    <cpList>
        <connected>false</connected>
        <connectedDttm>2017-12-25T17:53:32.383+08:00</connectedDttm>
        <cpNo>CP14</cpNo>
        <enabled>true</enabled>
        <lastReceivedDttm>2017-12-25T17:53:32.485+08:00</lastReceivedDttm>
        <lastSentDttm>2017-12-25T17:53:34.540+08:00</lastSentDttm>
        <status>Preparing</status>
        <statusDttm>2017-12-25T17:53:33.518+08:00</statusDttm>
    </cpList>
    <ctId>2</ctId>
    <enabled>true</enabled>
    <heartbeatInterval>600</heartbeatInterval>
    <octopusStatus>Unknown</octopusStatus>
    <printerStatus>Unknown</printerStatus>
    <receiptNo>49</receiptNo>
</ctModel>
